pymountain/__init__.py
pymountain/core/__init__.py
pymountain/core/data.py
pymountain/core/renderer.py
pymountain/renderers/__init__.py
pymountain/renderers/matplotlib_renderer.py
pymountain/utils/__init__.py
pymountain/utils/color_mapping.py
pymountain/utils/interpolation.py
pymountain-0.1.0.dist-info/METADATA
pymountain-0.1.0.dist-info/WHEEL
pymountain-0.1.0.dist-info/top_level.txt
pymountain-0.1.0.dist-info/RECORD
