Metadata-Version: 2.4
Name: pymountain
Version: 0.1.0
Summary: 功能强大、高度模块化的Python软件包，专注于山体地形数据的可视化 | A powerful, highly modular Python package focused on mountain terrain data visualization
Author-email: Miraitowa <2056978412@qq.com>
Project-URL: Homepage, https://github.com/Miraitowa-la/PyMountain
Project-URL: Repository, https://github.com/Miraitowa-la/PyMountain
Project-URL: Issues, https://github.com/Miraitowa-la/PyMountain/issues
Keywords: terrain,visualization,3d,contour,mountain,gis,matplotlib
Classifier: Development Status :: 3 - Alpha
Classifier: Intended Audience :: Science/Research
Classifier: Intended Audience :: Developers
Classifier: License :: OSI Approved :: MIT License
Classifier: Operating System :: OS Independent
Classifier: Programming Language :: Python :: 3
Classifier: Programming Language :: Python :: 3.8
Classifier: Programming Language :: Python :: 3.9
Classifier: Programming Language :: Python :: 3.10
Classifier: Programming Language :: Python :: 3.11
Classifier: Programming Language :: Python :: 3.12
Classifier: Topic :: Scientific/Engineering :: Visualization
Classifier: Topic :: Scientific/Engineering :: GIS
Requires-Python: >=3.8
Requires-Dist: numpy>=1.20.0
Requires-Dist: scipy>=1.7.0
Requires-Dist: matplotlib>=3.5.0
Provides-Extra: full
Requires-Dist: pandas>=1.3.0; extra == "full"
Requires-Dist: pyqtgraph>=0.12.0; extra == "full"
Requires-Dist: plotly>=5.0.0; extra == "full"
Requires-Dist: vispy>=0.9.0; extra == "full"
Requires-Dist: bokeh>=2.4.0; extra == "full"
Provides-Extra: pandas
Requires-Dist: pandas>=1.3.0; extra == "pandas"
Provides-Extra: interactive
Requires-Dist: pyqtgraph>=0.12.0; extra == "interactive"
Requires-Dist: vispy>=0.9.0; extra == "interactive"
Provides-Extra: web
Requires-Dist: plotly>=5.0.0; extra == "web"
Requires-Dist: bokeh>=2.4.0; extra == "web"
Provides-Extra: dev
Requires-Dist: pytest>=6.0; extra == "dev"
Requires-Dist: pytest-cov>=2.0; extra == "dev"
Requires-Dist: black>=21.0; extra == "dev"
Requires-Dist: flake8>=3.9; extra == "dev"
Requires-Dist: mypy>=0.910; extra == "dev"
Requires-Dist: sphinx>=4.0; extra == "dev"
Requires-Dist: sphinx-rtd-theme>=1.0; extra == "dev"
